makefile_checker/check.py
makefile_checker/checker.py
makefile_checker/exceptions.py
makefile_checker-0.0.2.dist-info/METADATA
makefile_checker-0.0.2.dist-info/WHEEL
makefile_checker-0.0.2.dist-info/entry_points.txt
makefile_checker-0.0.2.dist-info/RECORD
